hmcortexpy/__init__.py
hmcortexpy/middleware.py
hmcortexpy/session.py
hmcortexpy-0.1.0.dist-info/METADATA
hmcortexpy-0.1.0.dist-info/WHEEL
hmcortexpy-0.1.0.dist-info/top_level.txt
hmcortexpy-0.1.0.dist-info/RECORD
